{
  "eyebrow": "Our 2026 goal",
  "amount": "Rp 600,000,000",
  "subHtml": "to fund <strong>30 scholarships</strong> and a dedicated community manager for the year ahead.",
  "progress": 75,
  "progressLabelLeft": "Funding in progress",
  "studentLeft": "/assets/img/student-girl.webp",
  "studentLeftWidth": 417,
  "studentLeftHeight": 665,
  "studentRight": "/assets/img/student-boy.webp",
  "studentRightWidth": 508,
  "studentRightHeight": 679,
  "primaryCta": { "label": "Donate", "href": "#donate" },
  "secondaryCta": { "label": "See ways to give", "href": "#give" }
}
